superkwargs/__init__.py
superkwargs/annotations.py
superkwargs/decorator.py
superkwargs/exceptions.py
superkwargs/inject.py
superkwargs/typing.py
superkwargs-0.4.2.dist-info/METADATA
superkwargs-0.4.2.dist-info/WHEEL
superkwargs-0.4.2.dist-info/top_level.txt
superkwargs-0.4.2.dist-info/RECORD
